w266_project/__init__.py
w266_project/inference.py
w266_project/metrics.py
w266_project/test.py
w266_project/train.py
w266_project/utils.py
w266_project/dataset/__init__.py
w266_project/dataset/core.py
w266_project/preprocessor/__init__.py
w266_project/preprocessor/core.py
w266_project-0.0.1.dist-info/METADATA
w266_project-0.0.1.dist-info/WHEEL
w266_project-0.0.1.dist-info/top_level.txt
w266_project-0.0.1.dist-info/RECORD
