Metadata-Version: 2.1
Name: w266-project
Version: 0.0.1
Summary: UC Berkeley MIDS w266 Natural Language Processing project.
Classifier: Programming Language :: Python :: 3
